{
  "project_info": {
    "project_number": "338683949800",
    "firebase_url": "https://temphumid-554e2-default-rtdb.firebaseio.com",
    "project_id": "temphumid-554e2",
    "storage_bucket": "temphumid-554e2.appspot.com"
  },
  "client": [
    {
      "client_info": {
        "mobilesdk_app_id": "1:338683949800:android:fda5ca2e67f7c677284f5d",
        "android_client_info": {
          "package_name": "com.example.alarmapp"
        }
      },
      "oauth_client": [],
      "api_key": [
        {
          "current_key": "AIzaSyCs7FgDjxqCN3P16nKGdkTFLE70jvJ0ajo"
        }
      ],
      "services": {
        "appinvite_service": {
          "other_platform_oauth_client": []
        }
      }
    }
  ],
  "configuration_version": "1"
}